{"version": "1.1.0",
 "packagesDir": ".lake/packages",
 "packages":
 [{"url": "https://github.com/KislyjKisel/lean-pod",
   "type": "git",
   "subDir": null,
   "scope": "",
   "rev": "cb4734eaaf1088534c4bd05a61960d26279f934f",
   "name": "pod",
   "manifestFile": "lake-manifest.json",
   "inputRev": "cb4734e",
   "inherited": false,
   "configFile": "lakefile.lean"},
  {"url": "https://github.com/argumentcomputer/LSpec",
   "type": "git",
   "subDir": null,
   "scope": "",
   "rev": "a6652a48b5c67b0d8dd3930fad6390a97d127e8d",
   "name": "LSpec",
   "manifestFile": "lake-manifest.json",
   "inputRev": "a6652a4",
   "inherited": true,
   "configFile": "lakefile.toml"}],
 "name": "raylib",
 "lakeDir": ".lake"}
