{"version": 7,
 "packagesDir": ".lake/packages",
 "packages":
 [{"url": "https://github.com/KislyjKisel/libffi-lake",
   "type": "git",
   "subDir": null,
   "rev": "7c9fb2bee605d3785f459a55787966941cccfb6d",
   "name": "libffi",
   "manifestFile": "lake-manifest.json",
   "inputRev": "7c9fb2b",
   "inherited": false,
   "configFile": "lakefile.lean"},
  {"url": "https://github.com/KislyjKisel/lean-pod",
   "type": "git",
   "subDir": null,
   "rev": "117fababe3988edb66c2b346b61e7941de716f24",
   "name": "pod",
   "manifestFile": "lake-manifest.json",
   "inputRev": "117faba",
   "inherited": false,
   "configFile": "lakefile.lean"}],
 "name": "raylib",
 "lakeDir": ".lake"}
